numericalderivative/_DerivativeBenchmark.py
numericalderivative/_DumontetVignes.py
numericalderivative/_FiniteDifferenceFormula.py
numericalderivative/_FunctionWithArguments.py
numericalderivative/_GeneralFiniteDifference.py
numericalderivative/_GillMurraySaundersWright.py
numericalderivative/_ShiXieXuanNocedalForward.py
numericalderivative/_ShiXieXuanNocedalGeneral.py
numericalderivative/_SteplemanWinarsky.py
numericalderivative/__init__.py
numericalderivative-0.3.dist-info/LICENSE.txt
numericalderivative-0.3.dist-info/METADATA
numericalderivative-0.3.dist-info/WHEEL
numericalderivative-0.3.dist-info/top_level.txt
numericalderivative-0.3.dist-info/RECORD
