Metadata-Version: 2.1
Name: numericalderivative
Version: 0.3
Summary: Numerical differentiation
Home-page: https://github.com/mbaudin47/numericalderivative
Author: Michaël Baudin
Author-email: Michaël Baudin <michael.baudin@gmail.com>
License: GNU Lesser General Public License v3 (LGPLv3)
Project-URL: Homepage, https://github.com/mbaudin47/numericalderivative
Keywords: Numerical Differentiation,First Derivative,Finite Difference,Optimal Step Size,Numerical Analysis
Classifier: Development Status :: 3 - Alpha
Classifier: Environment :: Console
Classifier: License :: OSI Approved :: GNU Lesser General Public License v3 (LGPLv3)
Classifier: Intended Audience :: Science/Research
Classifier: Intended Audience :: Developers
Classifier: Natural Language :: English
Classifier: Programming Language :: Python :: 3
Classifier: Topic :: Scientific/Engineering
License-File: LICENSE.txt
Requires-Dist: numpy
Requires-Dist: scipy
Provides-Extra: cli
Requires-Dist: openturns; extra == "cli"
Requires-Dist: matplotlib; extra == "cli"
